lpaste/__init__.py
lpaste/__main__.py
lpaste/clipboard.py
lpaste/lpaste.py
lpaste/source.py
lpaste-5.3.0.dist-info/LICENSE
lpaste-5.3.0.dist-info/METADATA
lpaste-5.3.0.dist-info/WHEEL
lpaste-5.3.0.dist-info/entry_points.txt
lpaste-5.3.0.dist-info/top_level.txt
lpaste-5.3.0.dist-info/RECORD
