Metadata-Version: 2.1
Name: lpaste
Version: 5.3.0
Summary: Library Paste command-line client
Home-page: https://github.com/jaraco/lpaste
Author: Chris Mulligan
Author-email: chmullig@gmail.com
Maintainer: Jason R. Coombs
Maintainer-email: jaraco@jaraco.com
Classifier: Development Status :: 5 - Production/Stable
Classifier: Intended Audience :: Developers
Classifier: License :: OSI Approved :: MIT License
Classifier: Programming Language :: Python :: 3
Classifier: Programming Language :: Python :: 3 :: Only
Requires-Python: >=3.8
License-File: LICENSE
Requires-Dist: requests
Requires-Dist: keyring >=0.6
Requires-Dist: jaraco.context
Requires-Dist: jaraco.clipboard
Requires-Dist: importlib-metadata
Provides-Extra: docs
Requires-Dist: sphinx >=3.5 ; extra == 'docs'
Requires-Dist: jaraco.packaging >=9.3 ; extra == 'docs'
Requires-Dist: rst.linker >=1.9 ; extra == 'docs'
Requires-Dist: furo ; extra == 'docs'
Requires-Dist: sphinx-lint ; extra == 'docs'
Provides-Extra: testing
Requires-Dist: pytest >=6 ; extra == 'testing'
Requires-Dist: pytest-checkdocs >=2.4 ; extra == 'testing'
Requires-Dist: pytest-cov ; extra == 'testing'
Requires-Dist: pytest-enabler >=2.2 ; extra == 'testing'
Requires-Dist: pytest-ruff ; extra == 'testing'
Requires-Dist: types-requests ; extra == 'testing'
Requires-Dist: pytest-black >=0.3.7 ; (platform_python_implementation != "PyPy") and extra == 'testing'
Requires-Dist: pytest-mypy >=0.9.1 ; (platform_python_implementation != "PyPy") and extra == 'testing'
